hhqtrain
