Metadata-Version: 1.0
Name: hhqtrain
Version: 0.0.2
Summary: clinical trial information retriver
Home-page: http://github.com/
Author: hhq
Author-email: 779613975@qq.com
License: MIT
Platform: UNKNOWN
